_weakrefable.cpython-35m-darwin.so
weakrefable/__init__.py
weakrefable-0.0.1.dist-info/DESCRIPTION.rst
weakrefable-0.0.1.dist-info/METADATA
weakrefable-0.0.1.dist-info/RECORD
weakrefable-0.0.1.dist-info/WHEEL
weakrefable-0.0.1.dist-info/metadata.json
weakrefable-0.0.1.dist-info/pbr.json
weakrefable-0.0.1.dist-info/top_level.txt
