Metadata-Version: 2.0
Name: weakrefable
Version: 0.0.1
Summary: UNKNOWN
Home-page: https://github.com/Carreau/weakrefable
Author: Matthias Bussonnier
Author-email: bussonniermatthias@gmail.com
License: MIT
Keywords: weakref CPython
Platform: UNKNOWN
Requires-Python: >=3.4
